{"is_source_file": true, "format": "JavaScript (React JSX)", "description": "This file is the entry point for a React application, setting up the root DOM node and rendering the main App component within React's StrictMode.", "external_files": ["react", "react-dom/client", "./index.css", "./App"], "external_methods": ["ReactDOM.createRoot", "root.render"], "published": [], "classes": [], "methods": ["ReactDOM.createRoot", "root.render"], "calls": ["ReactDOM.createRoot", "root.render"], "search-terms": ["React", "ReactDOM", "src/index.js", "main entry point", "rendering React app"], "state": 2, "file_id": 10, "knowledge_revision": 24, "git_revision": "74cacf152227277f8f2eda52b1a6dedbb5a7ca7b", "ctags": [{"_type": "tag", "name": "root", "path": "/home/kavia/workspace/code-generation/universal-classifieds-platform-198777-198788/classifieds_frontend/src/index.js", "pattern": "/^const root = ReactDOM.createRoot(document.getElementById('root'));$/", "language": "JavaScript", "kind": "constant"}], "hash": "9fc5841375336fc175b49f8767a11383", "format-version": 4, "code-base-name": "classifieds_frontend", "filename": "classifieds_frontend/src/index.js", "revision_history": [{"24": "74cacf152227277f8f2eda52b1a6dedbb5a7ca7b"}]}